tiny_pytorch/__init__.py
tiny_pytorch/optim.py
tiny_pytorch/nn.py
tiny_pytorch/backend_numpy.py
tiny_pytorch/data.py
tiny_pytorch/ops.py
tiny_pytorch/backend_selection.py
tiny_pytorch/utils.py
tiny_pytorch/tensor.py
tiny_pytorch/ndarray_backend_cuda.cu
tiny_pytorch/ndarray_backend_cpu.cpp
tiny_pytorch/init.py
tiny_pytorch/ndarray_backend_cpu.cpython-313-x86_64-linux-gnu.so
tiny_pytorch/backend_ndarray/__init__.py
tiny_pytorch/backend_ndarray/ndarray.py
tiny_pytorch/backend_ndarray/ndarray_backend_numpy.py
tiny_pytorch/nlp/__init__.py
tiny_pytorch/nlp/models.py
tiny_pytorch/vision/__init__.py
tiny_pytorch/vision/models.py
tiny_pytorch-0.1.1.dist-info/METADATA
tiny_pytorch-0.1.1.dist-info/RECORD
tiny_pytorch-0.1.1.dist-info/top_level.txt
tiny_pytorch-0.1.1.dist-info/WHEEL
tiny_pytorch-0.1.1.dist-info/licenses/LICENSE
