Metadata-Version: 2.4
Name: tiny-pytorch
Version: 0.1.1
Summary: Mini Deep Learning framework similar to PyTorch
Author: Imad Dabbura
Author-email: Imad Dabbura <imad.dabbura@hotmail.com>
Requires-Python: >=3.13
License-File: LICENSE
Requires-Dist: numpy<3.0.0,>=2.2.3
Requires-Dist: setuptools>=61.0
Dynamic: author
Dynamic: license-file
Dynamic: requires-python
